<rr_gsb x="4" y="2" num_sides="4">
	<IPIN side="top" index="0" node_id="1023" mux_size="8">
		<driver_node type="CHANX" side="left" node_id="1720" index="0" segment_id="0"/>
		<driver_node type="CHANX" side="left" node_id="1667" index="1" segment_id="0"/>
		<driver_node type="CHANX" side="left" node_id="1702" index="12" segment_id="0"/>
		<driver_node type="CHANX" side="left" node_id="1713" index="13" segment_id="0"/>
		<driver_node type="CHANX" side="left" node_id="1726" index="24" segment_id="0"/>
		<driver_node type="CHANX" side="left" node_id="1691" index="25" segment_id="0"/>
		<driver_node type="CHANX" side="left" node_id="1708" index="36" segment_id="0"/>
		<driver_node type="CHANX" side="left" node_id="1719" index="37" segment_id="0"/>
	</IPIN>
	<IPIN side="top" index="1" node_id="1024" mux_size="8">
		<driver_node type="CHANX" side="left" node_id="1710" index="2" segment_id="0"/>
		<driver_node type="CHANX" side="left" node_id="1701" index="3" segment_id="0"/>
		<driver_node type="CHANX" side="left" node_id="1668" index="14" segment_id="0"/>
		<driver_node type="CHANX" side="left" node_id="1723" index="15" segment_id="0"/>
		<driver_node type="CHANX" side="left" node_id="1716" index="26" segment_id="0"/>
		<driver_node type="CHANX" side="left" node_id="1707" index="27" segment_id="0"/>
		<driver_node type="CHANX" side="left" node_id="1692" index="38" segment_id="0"/>
		<driver_node type="CHANX" side="left" node_id="1729" index="39" segment_id="0"/>
	</IPIN>
	<IPIN side="top" index="2" node_id="1025" mux_size="8">
		<driver_node type="CHANX" side="left" node_id="1720" index="0" segment_id="0"/>
		<driver_node type="CHANX" side="left" node_id="1667" index="1" segment_id="0"/>
		<driver_node type="CHANX" side="left" node_id="1700" index="4" segment_id="0"/>
		<driver_node type="CHANX" side="left" node_id="1711" index="5" segment_id="0"/>
		<driver_node type="CHANX" side="left" node_id="1724" index="16" segment_id="0"/>
		<driver_node type="CHANX" side="left" node_id="1683" index="17" segment_id="0"/>
		<driver_node type="CHANX" side="left" node_id="1706" index="28" segment_id="0"/>
		<driver_node type="CHANX" side="left" node_id="1717" index="29" segment_id="0"/>
	</IPIN>
	<IPIN side="top" index="3" node_id="1026" mux_size="8">
		<driver_node type="CHANX" side="left" node_id="1710" index="2" segment_id="0"/>
		<driver_node type="CHANX" side="left" node_id="1701" index="3" segment_id="0"/>
		<driver_node type="CHANX" side="left" node_id="1660" index="6" segment_id="0"/>
		<driver_node type="CHANX" side="left" node_id="1721" index="7" segment_id="0"/>
		<driver_node type="CHANX" side="left" node_id="1714" index="18" segment_id="0"/>
		<driver_node type="CHANX" side="left" node_id="1705" index="19" segment_id="0"/>
		<driver_node type="CHANX" side="left" node_id="1684" index="30" segment_id="0"/>
		<driver_node type="CHANX" side="left" node_id="1727" index="31" segment_id="0"/>
	</IPIN>
	<IPIN side="top" index="4" node_id="1027" mux_size="8">
		<driver_node type="CHANX" side="left" node_id="1700" index="4" segment_id="0"/>
		<driver_node type="CHANX" side="left" node_id="1711" index="5" segment_id="0"/>
		<driver_node type="CHANX" side="left" node_id="1722" index="8" segment_id="0"/>
		<driver_node type="CHANX" side="left" node_id="1675" index="9" segment_id="0"/>
		<driver_node type="CHANX" side="left" node_id="1704" index="20" segment_id="0"/>
		<driver_node type="CHANX" side="left" node_id="1715" index="21" segment_id="0"/>
		<driver_node type="CHANX" side="left" node_id="1728" index="32" segment_id="0"/>
		<driver_node type="CHANX" side="left" node_id="1699" index="33" segment_id="0"/>
	</IPIN>
	<IPIN side="top" index="5" node_id="1028" mux_size="8">
		<driver_node type="CHANX" side="left" node_id="1660" index="6" segment_id="0"/>
		<driver_node type="CHANX" side="left" node_id="1721" index="7" segment_id="0"/>
		<driver_node type="CHANX" side="left" node_id="1712" index="10" segment_id="0"/>
		<driver_node type="CHANX" side="left" node_id="1703" index="11" segment_id="0"/>
		<driver_node type="CHANX" side="left" node_id="1676" index="22" segment_id="0"/>
		<driver_node type="CHANX" side="left" node_id="1725" index="23" segment_id="0"/>
		<driver_node type="CHANX" side="left" node_id="1718" index="34" segment_id="0"/>
		<driver_node type="CHANX" side="left" node_id="1709" index="35" segment_id="0"/>
	</IPIN>
	<IPIN side="top" index="6" node_id="1029" mux_size="8">
		<driver_node type="CHANX" side="left" node_id="1722" index="8" segment_id="0"/>
		<driver_node type="CHANX" side="left" node_id="1675" index="9" segment_id="0"/>
		<driver_node type="CHANX" side="left" node_id="1702" index="12" segment_id="0"/>
		<driver_node type="CHANX" side="left" node_id="1713" index="13" segment_id="0"/>
		<driver_node type="CHANX" side="left" node_id="1726" index="24" segment_id="0"/>
		<driver_node type="CHANX" side="left" node_id="1691" index="25" segment_id="0"/>
		<driver_node type="CHANX" side="left" node_id="1708" index="36" segment_id="0"/>
		<driver_node type="CHANX" side="left" node_id="1719" index="37" segment_id="0"/>
	</IPIN>
	<IPIN side="top" index="7" node_id="1030" mux_size="8">
		<driver_node type="CHANX" side="left" node_id="1712" index="10" segment_id="0"/>
		<driver_node type="CHANX" side="left" node_id="1703" index="11" segment_id="0"/>
		<driver_node type="CHANX" side="left" node_id="1668" index="14" segment_id="0"/>
		<driver_node type="CHANX" side="left" node_id="1723" index="15" segment_id="0"/>
		<driver_node type="CHANX" side="left" node_id="1716" index="26" segment_id="0"/>
		<driver_node type="CHANX" side="left" node_id="1707" index="27" segment_id="0"/>
		<driver_node type="CHANX" side="left" node_id="1692" index="38" segment_id="0"/>
		<driver_node type="CHANX" side="left" node_id="1729" index="39" segment_id="0"/>
	</IPIN>
	<IPIN side="top" index="8" node_id="1031" mux_size="8">
		<driver_node type="CHANX" side="left" node_id="1720" index="0" segment_id="0"/>
		<driver_node type="CHANX" side="left" node_id="1667" index="1" segment_id="0"/>
		<driver_node type="CHANX" side="left" node_id="1702" index="12" segment_id="0"/>
		<driver_node type="CHANX" side="left" node_id="1713" index="13" segment_id="0"/>
		<driver_node type="CHANX" side="left" node_id="1724" index="16" segment_id="0"/>
		<driver_node type="CHANX" side="left" node_id="1683" index="17" segment_id="0"/>
		<driver_node type="CHANX" side="left" node_id="1706" index="28" segment_id="0"/>
		<driver_node type="CHANX" side="left" node_id="1717" index="29" segment_id="0"/>
	</IPIN>
	<IPIN side="top" index="9" node_id="1032" mux_size="8">
		<driver_node type="CHANX" side="left" node_id="1710" index="2" segment_id="0"/>
		<driver_node type="CHANX" side="left" node_id="1701" index="3" segment_id="0"/>
		<driver_node type="CHANX" side="left" node_id="1668" index="14" segment_id="0"/>
		<driver_node type="CHANX" side="left" node_id="1723" index="15" segment_id="0"/>
		<driver_node type="CHANX" side="left" node_id="1714" index="18" segment_id="0"/>
		<driver_node type="CHANX" side="left" node_id="1705" index="19" segment_id="0"/>
		<driver_node type="CHANX" side="left" node_id="1684" index="30" segment_id="0"/>
		<driver_node type="CHANX" side="left" node_id="1727" index="31" segment_id="0"/>
	</IPIN>
	<CHANY side="top" index="0" node_id="2200" segment_id="0" mux_size="10">
		<driver_node type="OPIN" side="top" index="0" node_id="996" grid_side="right"/>
		<driver_node type="OPIN" side="top" index="5" node_id="1062" grid_side="left"/>
		<driver_node type="OPIN" side="top" index="10" node_id="1067" grid_side="left"/>
		<driver_node type="CHANY" side="bottom" index="0" node_id="2190" segment_id="0"/>
		<driver_node type="CHANY" side="bottom" index="12" node_id="2160" segment_id="0"/>
		<driver_node type="CHANY" side="bottom" index="26" node_id="2174" segment_id="0"/>
		<driver_node type="CHANX" side="left" index="0" node_id="1720" segment_id="0"/>
		<driver_node type="CHANX" side="left" index="10" node_id="1712" segment_id="0"/>
		<driver_node type="CHANX" side="left" index="20" node_id="1704" segment_id="0"/>
		<driver_node type="CHANX" side="left" index="30" node_id="1684" segment_id="0"/>
	</CHANY>
	<CHANY side="top" index="2" node_id="2190" segment_id="0" mux_size="0">
		<driver_node type="CHANY" side="bottom" index="0" node_id="2190" segment_id="0"/>
	</CHANY>
	<CHANY side="top" index="4" node_id="2150" segment_id="0" mux_size="0">
		<driver_node type="CHANY" side="bottom" index="2" node_id="2150" segment_id="0"/>
	</CHANY>
	<CHANY side="top" index="6" node_id="2152" segment_id="0" mux_size="0">
		<driver_node type="CHANY" side="bottom" index="4" node_id="2152" segment_id="0"/>
	</CHANY>
	<CHANY side="top" index="8" node_id="2202" segment_id="0" mux_size="9">
		<driver_node type="OPIN" side="top" index="1" node_id="997" grid_side="right"/>
		<driver_node type="OPIN" side="top" index="6" node_id="1063" grid_side="left"/>
		<driver_node type="CHANY" side="bottom" index="2" node_id="2150" segment_id="0"/>
		<driver_node type="CHANY" side="bottom" index="16" node_id="2194" segment_id="0"/>
		<driver_node type="CHANY" side="bottom" index="28" node_id="2176" segment_id="0"/>
		<driver_node type="CHANX" side="left" index="8" node_id="1722" segment_id="0"/>
		<driver_node type="CHANX" side="left" index="18" node_id="1714" segment_id="0"/>
		<driver_node type="CHANX" side="left" index="28" node_id="1706" segment_id="0"/>
		<driver_node type="CHANX" side="left" index="38" node_id="1692" segment_id="0"/>
	</CHANY>
	<CHANY side="top" index="10" node_id="2192" segment_id="0" mux_size="0">
		<driver_node type="CHANY" side="bottom" index="8" node_id="2192" segment_id="0"/>
	</CHANY>
	<CHANY side="top" index="12" node_id="2158" segment_id="0" mux_size="0">
		<driver_node type="CHANY" side="bottom" index="10" node_id="2158" segment_id="0"/>
	</CHANY>
	<CHANY side="top" index="14" node_id="2160" segment_id="0" mux_size="0">
		<driver_node type="CHANY" side="bottom" index="12" node_id="2160" segment_id="0"/>
	</CHANY>
	<CHANY side="top" index="16" node_id="2204" segment_id="0" mux_size="9">
		<driver_node type="OPIN" side="top" index="2" node_id="998" grid_side="right"/>
		<driver_node type="OPIN" side="top" index="7" node_id="1064" grid_side="left"/>
		<driver_node type="CHANY" side="bottom" index="4" node_id="2152" segment_id="0"/>
		<driver_node type="CHANY" side="bottom" index="18" node_id="2166" segment_id="0"/>
		<driver_node type="CHANY" side="bottom" index="32" node_id="2198" segment_id="0"/>
		<driver_node type="CHANX" side="left" index="6" node_id="1660" segment_id="0"/>
		<driver_node type="CHANX" side="left" index="16" node_id="1724" segment_id="0"/>
		<driver_node type="CHANX" side="left" index="26" node_id="1716" segment_id="0"/>
		<driver_node type="CHANX" side="left" index="36" node_id="1708" segment_id="0"/>
	</CHANY>
	<CHANY side="top" index="18" node_id="2194" segment_id="0" mux_size="0">
		<driver_node type="CHANY" side="bottom" index="16" node_id="2194" segment_id="0"/>
	</CHANY>
	<CHANY side="top" index="20" node_id="2166" segment_id="0" mux_size="0">
		<driver_node type="CHANY" side="bottom" index="18" node_id="2166" segment_id="0"/>
	</CHANY>
	<CHANY side="top" index="22" node_id="2168" segment_id="0" mux_size="0">
		<driver_node type="CHANY" side="bottom" index="20" node_id="2168" segment_id="0"/>
	</CHANY>
	<CHANY side="top" index="24" node_id="2206" segment_id="0" mux_size="9">
		<driver_node type="OPIN" side="top" index="3" node_id="1060" grid_side="left"/>
		<driver_node type="OPIN" side="top" index="8" node_id="1065" grid_side="left"/>
		<driver_node type="CHANY" side="bottom" index="8" node_id="2192" segment_id="0"/>
		<driver_node type="CHANY" side="bottom" index="20" node_id="2168" segment_id="0"/>
		<driver_node type="CHANY" side="bottom" index="34" node_id="2182" segment_id="0"/>
		<driver_node type="CHANX" side="left" index="4" node_id="1700" segment_id="0"/>
		<driver_node type="CHANX" side="left" index="14" node_id="1668" segment_id="0"/>
		<driver_node type="CHANX" side="left" index="24" node_id="1726" segment_id="0"/>
		<driver_node type="CHANX" side="left" index="34" node_id="1718" segment_id="0"/>
	</CHANY>
	<CHANY side="top" index="26" node_id="2196" segment_id="0" mux_size="0">
		<driver_node type="CHANY" side="bottom" index="24" node_id="2196" segment_id="0"/>
	</CHANY>
	<CHANY side="top" index="28" node_id="2174" segment_id="0" mux_size="0">
		<driver_node type="CHANY" side="bottom" index="26" node_id="2174" segment_id="0"/>
	</CHANY>
	<CHANY side="top" index="30" node_id="2176" segment_id="0" mux_size="0">
		<driver_node type="CHANY" side="bottom" index="28" node_id="2176" segment_id="0"/>
	</CHANY>
	<CHANY side="top" index="32" node_id="2208" segment_id="0" mux_size="9">
		<driver_node type="OPIN" side="top" index="4" node_id="1061" grid_side="left"/>
		<driver_node type="OPIN" side="top" index="9" node_id="1066" grid_side="left"/>
		<driver_node type="CHANY" side="bottom" index="10" node_id="2158" segment_id="0"/>
		<driver_node type="CHANY" side="bottom" index="24" node_id="2196" segment_id="0"/>
		<driver_node type="CHANY" side="bottom" index="36" node_id="2184" segment_id="0"/>
		<driver_node type="CHANX" side="left" index="2" node_id="1710" segment_id="0"/>
		<driver_node type="CHANX" side="left" index="12" node_id="1702" segment_id="0"/>
		<driver_node type="CHANX" side="left" index="22" node_id="1676" segment_id="0"/>
		<driver_node type="CHANX" side="left" index="32" node_id="1728" segment_id="0"/>
	</CHANY>
	<CHANY side="top" index="34" node_id="2198" segment_id="0" mux_size="0">
		<driver_node type="CHANY" side="bottom" index="32" node_id="2198" segment_id="0"/>
	</CHANY>
	<CHANY side="top" index="36" node_id="2182" segment_id="0" mux_size="0">
		<driver_node type="CHANY" side="bottom" index="34" node_id="2182" segment_id="0"/>
	</CHANY>
	<CHANY side="top" index="38" node_id="2184" segment_id="0" mux_size="0">
		<driver_node type="CHANY" side="bottom" index="36" node_id="2184" segment_id="0"/>
	</CHANY>
	<IPIN side="right" index="0" node_id="1068" mux_size="8">
		<driver_node type="CHANY" side="top" node_id="2200" index="0" segment_id="0"/>
		<driver_node type="CHANY" side="top" node_id="2155" index="1" segment_id="0"/>
		<driver_node type="CHANY" side="top" node_id="2158" index="12" segment_id="0"/>
		<driver_node type="CHANY" side="top" node_id="2193" index="13" segment_id="0"/>
		<driver_node type="CHANY" side="top" node_id="2206" index="24" segment_id="0"/>
		<driver_node type="CHANY" side="top" node_id="2179" index="25" segment_id="0"/>
		<driver_node type="CHANY" side="top" node_id="2182" index="36" segment_id="0"/>
		<driver_node type="CHANY" side="top" node_id="2199" index="37" segment_id="0"/>
	</IPIN>
	<IPIN side="right" index="1" node_id="1069" mux_size="8">
		<driver_node type="CHANY" side="top" node_id="2190" index="2" segment_id="0"/>
		<driver_node type="CHANY" side="top" node_id="2157" index="3" segment_id="0"/>
		<driver_node type="CHANY" side="top" node_id="2160" index="14" segment_id="0"/>
		<driver_node type="CHANY" side="top" node_id="2203" index="15" segment_id="0"/>
		<driver_node type="CHANY" side="top" node_id="2196" index="26" segment_id="0"/>
		<driver_node type="CHANY" side="top" node_id="2181" index="27" segment_id="0"/>
		<driver_node type="CHANY" side="top" node_id="2184" index="38" segment_id="0"/>
		<driver_node type="CHANY" side="top" node_id="2209" index="39" segment_id="0"/>
	</IPIN>
	<IPIN side="right" index="2" node_id="1070" mux_size="8">
		<driver_node type="CHANY" side="top" node_id="2200" index="0" segment_id="0"/>
		<driver_node type="CHANY" side="top" node_id="2155" index="1" segment_id="0"/>
		<driver_node type="CHANY" side="top" node_id="2150" index="4" segment_id="0"/>
		<driver_node type="CHANY" side="top" node_id="2191" index="5" segment_id="0"/>
		<driver_node type="CHANY" side="top" node_id="2204" index="16" segment_id="0"/>
		<driver_node type="CHANY" side="top" node_id="2171" index="17" segment_id="0"/>
		<driver_node type="CHANY" side="top" node_id="2174" index="28" segment_id="0"/>
		<driver_node type="CHANY" side="top" node_id="2197" index="29" segment_id="0"/>
	</IPIN>
	<IPIN side="right" index="3" node_id="1071" mux_size="8">
		<driver_node type="CHANY" side="top" node_id="2190" index="2" segment_id="0"/>
		<driver_node type="CHANY" side="top" node_id="2157" index="3" segment_id="0"/>
		<driver_node type="CHANY" side="top" node_id="2152" index="6" segment_id="0"/>
		<driver_node type="CHANY" side="top" node_id="2201" index="7" segment_id="0"/>
		<driver_node type="CHANY" side="top" node_id="2194" index="18" segment_id="0"/>
		<driver_node type="CHANY" side="top" node_id="2173" index="19" segment_id="0"/>
		<driver_node type="CHANY" side="top" node_id="2176" index="30" segment_id="0"/>
		<driver_node type="CHANY" side="top" node_id="2207" index="31" segment_id="0"/>
	</IPIN>
	<IPIN side="right" index="4" node_id="1072" mux_size="8">
		<driver_node type="CHANY" side="top" node_id="2150" index="4" segment_id="0"/>
		<driver_node type="CHANY" side="top" node_id="2191" index="5" segment_id="0"/>
		<driver_node type="CHANY" side="top" node_id="2202" index="8" segment_id="0"/>
		<driver_node type="CHANY" side="top" node_id="2163" index="9" segment_id="0"/>
		<driver_node type="CHANY" side="top" node_id="2166" index="20" segment_id="0"/>
		<driver_node type="CHANY" side="top" node_id="2195" index="21" segment_id="0"/>
		<driver_node type="CHANY" side="top" node_id="2208" index="32" segment_id="0"/>
		<driver_node type="CHANY" side="top" node_id="2187" index="33" segment_id="0"/>
	</IPIN>
	<IPIN side="right" index="5" node_id="1073" mux_size="8">
		<driver_node type="CHANY" side="top" node_id="2152" index="6" segment_id="0"/>
		<driver_node type="CHANY" side="top" node_id="2201" index="7" segment_id="0"/>
		<driver_node type="CHANY" side="top" node_id="2192" index="10" segment_id="0"/>
		<driver_node type="CHANY" side="top" node_id="2165" index="11" segment_id="0"/>
		<driver_node type="CHANY" side="top" node_id="2168" index="22" segment_id="0"/>
		<driver_node type="CHANY" side="top" node_id="2205" index="23" segment_id="0"/>
		<driver_node type="CHANY" side="top" node_id="2198" index="34" segment_id="0"/>
		<driver_node type="CHANY" side="top" node_id="2189" index="35" segment_id="0"/>
	</IPIN>
	<IPIN side="right" index="6" node_id="1074" mux_size="8">
		<driver_node type="CHANY" side="top" node_id="2202" index="8" segment_id="0"/>
		<driver_node type="CHANY" side="top" node_id="2163" index="9" segment_id="0"/>
		<driver_node type="CHANY" side="top" node_id="2158" index="12" segment_id="0"/>
		<driver_node type="CHANY" side="top" node_id="2193" index="13" segment_id="0"/>
		<driver_node type="CHANY" side="top" node_id="2206" index="24" segment_id="0"/>
		<driver_node type="CHANY" side="top" node_id="2179" index="25" segment_id="0"/>
		<driver_node type="CHANY" side="top" node_id="2182" index="36" segment_id="0"/>
		<driver_node type="CHANY" side="top" node_id="2199" index="37" segment_id="0"/>
	</IPIN>
	<IPIN side="right" index="7" node_id="1075" mux_size="8">
		<driver_node type="CHANY" side="top" node_id="2192" index="10" segment_id="0"/>
		<driver_node type="CHANY" side="top" node_id="2165" index="11" segment_id="0"/>
		<driver_node type="CHANY" side="top" node_id="2160" index="14" segment_id="0"/>
		<driver_node type="CHANY" side="top" node_id="2203" index="15" segment_id="0"/>
		<driver_node type="CHANY" side="top" node_id="2196" index="26" segment_id="0"/>
		<driver_node type="CHANY" side="top" node_id="2181" index="27" segment_id="0"/>
		<driver_node type="CHANY" side="top" node_id="2184" index="38" segment_id="0"/>
		<driver_node type="CHANY" side="top" node_id="2209" index="39" segment_id="0"/>
	</IPIN>
	<IPIN side="bottom" index="0" node_id="687" mux_size="8">
		<driver_node type="CHANX" side="left" node_id="1700" index="4" segment_id="0"/>
		<driver_node type="CHANX" side="left" node_id="1711" index="5" segment_id="0"/>
		<driver_node type="CHANX" side="left" node_id="1724" index="16" segment_id="0"/>
		<driver_node type="CHANX" side="left" node_id="1683" index="17" segment_id="0"/>
		<driver_node type="CHANX" side="left" node_id="1704" index="20" segment_id="0"/>
		<driver_node type="CHANX" side="left" node_id="1715" index="21" segment_id="0"/>
		<driver_node type="CHANX" side="left" node_id="1728" index="32" segment_id="0"/>
		<driver_node type="CHANX" side="left" node_id="1699" index="33" segment_id="0"/>
	</IPIN>
	<IPIN side="bottom" index="1" node_id="688" mux_size="8">
		<driver_node type="CHANX" side="left" node_id="1660" index="6" segment_id="0"/>
		<driver_node type="CHANX" side="left" node_id="1721" index="7" segment_id="0"/>
		<driver_node type="CHANX" side="left" node_id="1714" index="18" segment_id="0"/>
		<driver_node type="CHANX" side="left" node_id="1705" index="19" segment_id="0"/>
		<driver_node type="CHANX" side="left" node_id="1676" index="22" segment_id="0"/>
		<driver_node type="CHANX" side="left" node_id="1725" index="23" segment_id="0"/>
		<driver_node type="CHANX" side="left" node_id="1718" index="34" segment_id="0"/>
		<driver_node type="CHANX" side="left" node_id="1709" index="35" segment_id="0"/>
	</IPIN>
	<IPIN side="bottom" index="2" node_id="689" mux_size="8">
		<driver_node type="CHANX" side="left" node_id="1722" index="8" segment_id="0"/>
		<driver_node type="CHANX" side="left" node_id="1675" index="9" segment_id="0"/>
		<driver_node type="CHANX" side="left" node_id="1704" index="20" segment_id="0"/>
		<driver_node type="CHANX" side="left" node_id="1715" index="21" segment_id="0"/>
		<driver_node type="CHANX" side="left" node_id="1726" index="24" segment_id="0"/>
		<driver_node type="CHANX" side="left" node_id="1691" index="25" segment_id="0"/>
		<driver_node type="CHANX" side="left" node_id="1708" index="36" segment_id="0"/>
		<driver_node type="CHANX" side="left" node_id="1719" index="37" segment_id="0"/>
	</IPIN>
	<IPIN side="bottom" index="3" node_id="690" mux_size="8">
		<driver_node type="CHANX" side="left" node_id="1712" index="10" segment_id="0"/>
		<driver_node type="CHANX" side="left" node_id="1703" index="11" segment_id="0"/>
		<driver_node type="CHANX" side="left" node_id="1676" index="22" segment_id="0"/>
		<driver_node type="CHANX" side="left" node_id="1725" index="23" segment_id="0"/>
		<driver_node type="CHANX" side="left" node_id="1716" index="26" segment_id="0"/>
		<driver_node type="CHANX" side="left" node_id="1707" index="27" segment_id="0"/>
		<driver_node type="CHANX" side="left" node_id="1692" index="38" segment_id="0"/>
		<driver_node type="CHANX" side="left" node_id="1729" index="39" segment_id="0"/>
	</IPIN>
	<IPIN side="bottom" index="4" node_id="691" mux_size="8">
		<driver_node type="CHANX" side="left" node_id="1720" index="0" segment_id="0"/>
		<driver_node type="CHANX" side="left" node_id="1667" index="1" segment_id="0"/>
		<driver_node type="CHANX" side="left" node_id="1702" index="12" segment_id="0"/>
		<driver_node type="CHANX" side="left" node_id="1713" index="13" segment_id="0"/>
		<driver_node type="CHANX" side="left" node_id="1726" index="24" segment_id="0"/>
		<driver_node type="CHANX" side="left" node_id="1691" index="25" segment_id="0"/>
		<driver_node type="CHANX" side="left" node_id="1706" index="28" segment_id="0"/>
		<driver_node type="CHANX" side="left" node_id="1717" index="29" segment_id="0"/>
	</IPIN>
	<IPIN side="bottom" index="5" node_id="692" mux_size="8">
		<driver_node type="CHANX" side="left" node_id="1710" index="2" segment_id="0"/>
		<driver_node type="CHANX" side="left" node_id="1701" index="3" segment_id="0"/>
		<driver_node type="CHANX" side="left" node_id="1668" index="14" segment_id="0"/>
		<driver_node type="CHANX" side="left" node_id="1723" index="15" segment_id="0"/>
		<driver_node type="CHANX" side="left" node_id="1716" index="26" segment_id="0"/>
		<driver_node type="CHANX" side="left" node_id="1707" index="27" segment_id="0"/>
		<driver_node type="CHANX" side="left" node_id="1684" index="30" segment_id="0"/>
		<driver_node type="CHANX" side="left" node_id="1727" index="31" segment_id="0"/>
	</IPIN>
	<IPIN side="bottom" index="6" node_id="693" mux_size="8">
		<driver_node type="CHANX" side="left" node_id="1700" index="4" segment_id="0"/>
		<driver_node type="CHANX" side="left" node_id="1711" index="5" segment_id="0"/>
		<driver_node type="CHANX" side="left" node_id="1724" index="16" segment_id="0"/>
		<driver_node type="CHANX" side="left" node_id="1683" index="17" segment_id="0"/>
		<driver_node type="CHANX" side="left" node_id="1706" index="28" segment_id="0"/>
		<driver_node type="CHANX" side="left" node_id="1717" index="29" segment_id="0"/>
		<driver_node type="CHANX" side="left" node_id="1728" index="32" segment_id="0"/>
		<driver_node type="CHANX" side="left" node_id="1699" index="33" segment_id="0"/>
	</IPIN>
	<IPIN side="bottom" index="7" node_id="694" mux_size="8">
		<driver_node type="CHANX" side="left" node_id="1660" index="6" segment_id="0"/>
		<driver_node type="CHANX" side="left" node_id="1721" index="7" segment_id="0"/>
		<driver_node type="CHANX" side="left" node_id="1714" index="18" segment_id="0"/>
		<driver_node type="CHANX" side="left" node_id="1705" index="19" segment_id="0"/>
		<driver_node type="CHANX" side="left" node_id="1684" index="30" segment_id="0"/>
		<driver_node type="CHANX" side="left" node_id="1727" index="31" segment_id="0"/>
		<driver_node type="CHANX" side="left" node_id="1718" index="34" segment_id="0"/>
		<driver_node type="CHANX" side="left" node_id="1709" index="35" segment_id="0"/>
	</IPIN>
	<IPIN side="bottom" index="8" node_id="695" mux_size="8">
		<driver_node type="CHANX" side="left" node_id="1722" index="8" segment_id="0"/>
		<driver_node type="CHANX" side="left" node_id="1675" index="9" segment_id="0"/>
		<driver_node type="CHANX" side="left" node_id="1704" index="20" segment_id="0"/>
		<driver_node type="CHANX" side="left" node_id="1715" index="21" segment_id="0"/>
		<driver_node type="CHANX" side="left" node_id="1728" index="32" segment_id="0"/>
		<driver_node type="CHANX" side="left" node_id="1699" index="33" segment_id="0"/>
		<driver_node type="CHANX" side="left" node_id="1708" index="36" segment_id="0"/>
		<driver_node type="CHANX" side="left" node_id="1719" index="37" segment_id="0"/>
	</IPIN>
	<IPIN side="bottom" index="9" node_id="696" mux_size="8">
		<driver_node type="CHANX" side="left" node_id="1712" index="10" segment_id="0"/>
		<driver_node type="CHANX" side="left" node_id="1703" index="11" segment_id="0"/>
		<driver_node type="CHANX" side="left" node_id="1676" index="22" segment_id="0"/>
		<driver_node type="CHANX" side="left" node_id="1725" index="23" segment_id="0"/>
		<driver_node type="CHANX" side="left" node_id="1718" index="34" segment_id="0"/>
		<driver_node type="CHANX" side="left" node_id="1709" index="35" segment_id="0"/>
		<driver_node type="CHANX" side="left" node_id="1692" index="38" segment_id="0"/>
		<driver_node type="CHANX" side="left" node_id="1729" index="39" segment_id="0"/>
	</IPIN>
	<CHANY side="bottom" index="1" node_id="2153" segment_id="0" mux_size="10">
		<driver_node type="CHANY" side="top" index="1" node_id="2155" segment_id="0"/>
		<driver_node type="CHANY" side="top" index="13" node_id="2193" segment_id="0"/>
		<driver_node type="CHANY" side="top" index="27" node_id="2181" segment_id="0"/>
		<driver_node type="OPIN" side="bottom" index="0" node_id="744" grid_side="left"/>
		<driver_node type="OPIN" side="bottom" index="5" node_id="749" grid_side="left"/>
		<driver_node type="OPIN" side="bottom" index="10" node_id="682" grid_side="right"/>
		<driver_node type="CHANX" side="left" index="2" node_id="1710" segment_id="0"/>
		<driver_node type="CHANX" side="left" index="12" node_id="1702" segment_id="0"/>
		<driver_node type="CHANX" side="left" index="22" node_id="1676" segment_id="0"/>
		<driver_node type="CHANX" side="left" index="32" node_id="1728" segment_id="0"/>
	</CHANY>
	<CHANY side="bottom" index="3" node_id="2155" segment_id="0" mux_size="0">
		<driver_node type="CHANY" side="top" index="1" node_id="2155" segment_id="0"/>
	</CHANY>
	<CHANY side="bottom" index="5" node_id="2157" segment_id="0" mux_size="0">
		<driver_node type="CHANY" side="top" index="3" node_id="2157" segment_id="0"/>
	</CHANY>
	<CHANY side="bottom" index="7" node_id="2191" segment_id="0" mux_size="0">
		<driver_node type="CHANY" side="top" index="5" node_id="2191" segment_id="0"/>
	</CHANY>
	<CHANY side="bottom" index="9" node_id="2161" segment_id="0" mux_size="9">
		<driver_node type="CHANY" side="top" index="3" node_id="2157" segment_id="0"/>
		<driver_node type="CHANY" side="top" index="17" node_id="2171" segment_id="0"/>
		<driver_node type="CHANY" side="top" index="29" node_id="2197" segment_id="0"/>
		<driver_node type="OPIN" side="bottom" index="1" node_id="745" grid_side="left"/>
		<driver_node type="OPIN" side="bottom" index="6" node_id="750" grid_side="left"/>
		<driver_node type="CHANX" side="left" index="4" node_id="1700" segment_id="0"/>
		<driver_node type="CHANX" side="left" index="14" node_id="1668" segment_id="0"/>
		<driver_node type="CHANX" side="left" index="24" node_id="1726" segment_id="0"/>
		<driver_node type="CHANX" side="left" index="34" node_id="1718" segment_id="0"/>
	</CHANY>
	<CHANY side="bottom" index="11" node_id="2163" segment_id="0" mux_size="0">
		<driver_node type="CHANY" side="top" index="9" node_id="2163" segment_id="0"/>
	</CHANY>
	<CHANY side="bottom" index="13" node_id="2165" segment_id="0" mux_size="0">
		<driver_node type="CHANY" side="top" index="11" node_id="2165" segment_id="0"/>
	</CHANY>
	<CHANY side="bottom" index="15" node_id="2193" segment_id="0" mux_size="0">
		<driver_node type="CHANY" side="top" index="13" node_id="2193" segment_id="0"/>
	</CHANY>
	<CHANY side="bottom" index="17" node_id="2169" segment_id="0" mux_size="9">
		<driver_node type="CHANY" side="top" index="5" node_id="2191" segment_id="0"/>
		<driver_node type="CHANY" side="top" index="19" node_id="2173" segment_id="0"/>
		<driver_node type="CHANY" side="top" index="33" node_id="2187" segment_id="0"/>
		<driver_node type="OPIN" side="bottom" index="2" node_id="746" grid_side="left"/>
		<driver_node type="OPIN" side="bottom" index="7" node_id="751" grid_side="left"/>
		<driver_node type="CHANX" side="left" index="6" node_id="1660" segment_id="0"/>
		<driver_node type="CHANX" side="left" index="16" node_id="1724" segment_id="0"/>
		<driver_node type="CHANX" side="left" index="26" node_id="1716" segment_id="0"/>
		<driver_node type="CHANX" side="left" index="36" node_id="1708" segment_id="0"/>
	</CHANY>
	<CHANY side="bottom" index="19" node_id="2171" segment_id="0" mux_size="0">
		<driver_node type="CHANY" side="top" index="17" node_id="2171" segment_id="0"/>
	</CHANY>
	<CHANY side="bottom" index="21" node_id="2173" segment_id="0" mux_size="0">
		<driver_node type="CHANY" side="top" index="19" node_id="2173" segment_id="0"/>
	</CHANY>
	<CHANY side="bottom" index="23" node_id="2195" segment_id="0" mux_size="0">
		<driver_node type="CHANY" side="top" index="21" node_id="2195" segment_id="0"/>
	</CHANY>
	<CHANY side="bottom" index="25" node_id="2177" segment_id="0" mux_size="9">
		<driver_node type="CHANY" side="top" index="9" node_id="2163" segment_id="0"/>
		<driver_node type="CHANY" side="top" index="21" node_id="2195" segment_id="0"/>
		<driver_node type="CHANY" side="top" index="35" node_id="2189" segment_id="0"/>
		<driver_node type="OPIN" side="bottom" index="3" node_id="747" grid_side="left"/>
		<driver_node type="OPIN" side="bottom" index="8" node_id="680" grid_side="right"/>
		<driver_node type="CHANX" side="left" index="8" node_id="1722" segment_id="0"/>
		<driver_node type="CHANX" side="left" index="18" node_id="1714" segment_id="0"/>
		<driver_node type="CHANX" side="left" index="28" node_id="1706" segment_id="0"/>
		<driver_node type="CHANX" side="left" index="38" node_id="1692" segment_id="0"/>
	</CHANY>
	<CHANY side="bottom" index="27" node_id="2179" segment_id="0" mux_size="0">
		<driver_node type="CHANY" side="top" index="25" node_id="2179" segment_id="0"/>
	</CHANY>
	<CHANY side="bottom" index="29" node_id="2181" segment_id="0" mux_size="0">
		<driver_node type="CHANY" side="top" index="27" node_id="2181" segment_id="0"/>
	</CHANY>
	<CHANY side="bottom" index="31" node_id="2197" segment_id="0" mux_size="0">
		<driver_node type="CHANY" side="top" index="29" node_id="2197" segment_id="0"/>
	</CHANY>
	<CHANY side="bottom" index="33" node_id="2185" segment_id="0" mux_size="9">
		<driver_node type="CHANY" side="top" index="11" node_id="2165" segment_id="0"/>
		<driver_node type="CHANY" side="top" index="25" node_id="2179" segment_id="0"/>
		<driver_node type="CHANY" side="top" index="37" node_id="2199" segment_id="0"/>
		<driver_node type="OPIN" side="bottom" index="4" node_id="748" grid_side="left"/>
		<driver_node type="OPIN" side="bottom" index="9" node_id="681" grid_side="right"/>
		<driver_node type="CHANX" side="left" index="0" node_id="1720" segment_id="0"/>
		<driver_node type="CHANX" side="left" index="10" node_id="1712" segment_id="0"/>
		<driver_node type="CHANX" side="left" index="20" node_id="1704" segment_id="0"/>
		<driver_node type="CHANX" side="left" index="30" node_id="1684" segment_id="0"/>
	</CHANY>
	<CHANY side="bottom" index="35" node_id="2187" segment_id="0" mux_size="0">
		<driver_node type="CHANY" side="top" index="33" node_id="2187" segment_id="0"/>
	</CHANY>
	<CHANY side="bottom" index="37" node_id="2189" segment_id="0" mux_size="0">
		<driver_node type="CHANY" side="top" index="35" node_id="2189" segment_id="0"/>
	</CHANY>
	<CHANY side="bottom" index="39" node_id="2199" segment_id="0" mux_size="0">
		<driver_node type="CHANY" side="top" index="37" node_id="2199" segment_id="0"/>
	</CHANY>
	<IPIN side="left" index="0" node_id="1013" mux_size="8">
		<driver_node type="CHANY" side="top" node_id="2200" index="0" segment_id="0"/>
		<driver_node type="CHANY" side="top" node_id="2155" index="1" segment_id="0"/>
		<driver_node type="CHANY" side="top" node_id="2158" index="12" segment_id="0"/>
		<driver_node type="CHANY" side="top" node_id="2193" index="13" segment_id="0"/>
		<driver_node type="CHANY" side="top" node_id="2204" index="16" segment_id="0"/>
		<driver_node type="CHANY" side="top" node_id="2171" index="17" segment_id="0"/>
		<driver_node type="CHANY" side="top" node_id="2174" index="28" segment_id="0"/>
		<driver_node type="CHANY" side="top" node_id="2197" index="29" segment_id="0"/>
	</IPIN>
	<IPIN side="left" index="1" node_id="1014" mux_size="8">
		<driver_node type="CHANY" side="top" node_id="2190" index="2" segment_id="0"/>
		<driver_node type="CHANY" side="top" node_id="2157" index="3" segment_id="0"/>
		<driver_node type="CHANY" side="top" node_id="2160" index="14" segment_id="0"/>
		<driver_node type="CHANY" side="top" node_id="2203" index="15" segment_id="0"/>
		<driver_node type="CHANY" side="top" node_id="2194" index="18" segment_id="0"/>
		<driver_node type="CHANY" side="top" node_id="2173" index="19" segment_id="0"/>
		<driver_node type="CHANY" side="top" node_id="2176" index="30" segment_id="0"/>
		<driver_node type="CHANY" side="top" node_id="2207" index="31" segment_id="0"/>
	</IPIN>
	<IPIN side="left" index="2" node_id="1015" mux_size="8">
		<driver_node type="CHANY" side="top" node_id="2150" index="4" segment_id="0"/>
		<driver_node type="CHANY" side="top" node_id="2191" index="5" segment_id="0"/>
		<driver_node type="CHANY" side="top" node_id="2204" index="16" segment_id="0"/>
		<driver_node type="CHANY" side="top" node_id="2171" index="17" segment_id="0"/>
		<driver_node type="CHANY" side="top" node_id="2166" index="20" segment_id="0"/>
		<driver_node type="CHANY" side="top" node_id="2195" index="21" segment_id="0"/>
		<driver_node type="CHANY" side="top" node_id="2208" index="32" segment_id="0"/>
		<driver_node type="CHANY" side="top" node_id="2187" index="33" segment_id="0"/>
	</IPIN>
	<IPIN side="left" index="3" node_id="1016" mux_size="8">
		<driver_node type="CHANY" side="top" node_id="2152" index="6" segment_id="0"/>
		<driver_node type="CHANY" side="top" node_id="2201" index="7" segment_id="0"/>
		<driver_node type="CHANY" side="top" node_id="2194" index="18" segment_id="0"/>
		<driver_node type="CHANY" side="top" node_id="2173" index="19" segment_id="0"/>
		<driver_node type="CHANY" side="top" node_id="2168" index="22" segment_id="0"/>
		<driver_node type="CHANY" side="top" node_id="2205" index="23" segment_id="0"/>
		<driver_node type="CHANY" side="top" node_id="2198" index="34" segment_id="0"/>
		<driver_node type="CHANY" side="top" node_id="2189" index="35" segment_id="0"/>
	</IPIN>
	<IPIN side="left" index="4" node_id="1017" mux_size="8">
		<driver_node type="CHANY" side="top" node_id="2202" index="8" segment_id="0"/>
		<driver_node type="CHANY" side="top" node_id="2163" index="9" segment_id="0"/>
		<driver_node type="CHANY" side="top" node_id="2166" index="20" segment_id="0"/>
		<driver_node type="CHANY" side="top" node_id="2195" index="21" segment_id="0"/>
		<driver_node type="CHANY" side="top" node_id="2206" index="24" segment_id="0"/>
		<driver_node type="CHANY" side="top" node_id="2179" index="25" segment_id="0"/>
		<driver_node type="CHANY" side="top" node_id="2182" index="36" segment_id="0"/>
		<driver_node type="CHANY" side="top" node_id="2199" index="37" segment_id="0"/>
	</IPIN>
	<IPIN side="left" index="5" node_id="1018" mux_size="8">
		<driver_node type="CHANY" side="top" node_id="2192" index="10" segment_id="0"/>
		<driver_node type="CHANY" side="top" node_id="2165" index="11" segment_id="0"/>
		<driver_node type="CHANY" side="top" node_id="2168" index="22" segment_id="0"/>
		<driver_node type="CHANY" side="top" node_id="2205" index="23" segment_id="0"/>
		<driver_node type="CHANY" side="top" node_id="2196" index="26" segment_id="0"/>
		<driver_node type="CHANY" side="top" node_id="2181" index="27" segment_id="0"/>
		<driver_node type="CHANY" side="top" node_id="2184" index="38" segment_id="0"/>
		<driver_node type="CHANY" side="top" node_id="2209" index="39" segment_id="0"/>
	</IPIN>
	<IPIN side="left" index="6" node_id="1019" mux_size="8">
		<driver_node type="CHANY" side="top" node_id="2200" index="0" segment_id="0"/>
		<driver_node type="CHANY" side="top" node_id="2155" index="1" segment_id="0"/>
		<driver_node type="CHANY" side="top" node_id="2158" index="12" segment_id="0"/>
		<driver_node type="CHANY" side="top" node_id="2193" index="13" segment_id="0"/>
		<driver_node type="CHANY" side="top" node_id="2206" index="24" segment_id="0"/>
		<driver_node type="CHANY" side="top" node_id="2179" index="25" segment_id="0"/>
		<driver_node type="CHANY" side="top" node_id="2174" index="28" segment_id="0"/>
		<driver_node type="CHANY" side="top" node_id="2197" index="29" segment_id="0"/>
	</IPIN>
	<IPIN side="left" index="7" node_id="1020" mux_size="8">
		<driver_node type="CHANY" side="top" node_id="2190" index="2" segment_id="0"/>
		<driver_node type="CHANY" side="top" node_id="2157" index="3" segment_id="0"/>
		<driver_node type="CHANY" side="top" node_id="2160" index="14" segment_id="0"/>
		<driver_node type="CHANY" side="top" node_id="2203" index="15" segment_id="0"/>
		<driver_node type="CHANY" side="top" node_id="2196" index="26" segment_id="0"/>
		<driver_node type="CHANY" side="top" node_id="2181" index="27" segment_id="0"/>
		<driver_node type="CHANY" side="top" node_id="2176" index="30" segment_id="0"/>
		<driver_node type="CHANY" side="top" node_id="2207" index="31" segment_id="0"/>
	</IPIN>
	<IPIN side="left" index="8" node_id="1021" mux_size="8">
		<driver_node type="CHANY" side="top" node_id="2150" index="4" segment_id="0"/>
		<driver_node type="CHANY" side="top" node_id="2191" index="5" segment_id="0"/>
		<driver_node type="CHANY" side="top" node_id="2204" index="16" segment_id="0"/>
		<driver_node type="CHANY" side="top" node_id="2171" index="17" segment_id="0"/>
		<driver_node type="CHANY" side="top" node_id="2174" index="28" segment_id="0"/>
		<driver_node type="CHANY" side="top" node_id="2197" index="29" segment_id="0"/>
		<driver_node type="CHANY" side="top" node_id="2208" index="32" segment_id="0"/>
		<driver_node type="CHANY" side="top" node_id="2187" index="33" segment_id="0"/>
	</IPIN>
	<IPIN side="left" index="9" node_id="1022" mux_size="8">
		<driver_node type="CHANY" side="top" node_id="2152" index="6" segment_id="0"/>
		<driver_node type="CHANY" side="top" node_id="2201" index="7" segment_id="0"/>
		<driver_node type="CHANY" side="top" node_id="2194" index="18" segment_id="0"/>
		<driver_node type="CHANY" side="top" node_id="2173" index="19" segment_id="0"/>
		<driver_node type="CHANY" side="top" node_id="2176" index="30" segment_id="0"/>
		<driver_node type="CHANY" side="top" node_id="2207" index="31" segment_id="0"/>
		<driver_node type="CHANY" side="top" node_id="2198" index="34" segment_id="0"/>
		<driver_node type="CHANY" side="top" node_id="2189" index="35" segment_id="0"/>
	</IPIN>
	<CHANX side="left" index="1" node_id="1667" segment_id="0" mux_size="3">
		<driver_node type="CHANY" side="top" index="1" node_id="2155" segment_id="0"/>
		<driver_node type="CHANY" side="top" index="7" node_id="2201" segment_id="0"/>
		<driver_node type="OPIN" side="left" index="0" node_id="999" grid_side="bottom"/>
	</CHANX>
	<CHANX side="left" index="3" node_id="1701" segment_id="0" mux_size="3">
		<driver_node type="CHANY" side="bottom" index="0" node_id="2190" segment_id="0"/>
		<driver_node type="CHANY" side="bottom" index="6" node_id="2154" segment_id="0"/>
		<driver_node type="OPIN" side="left" index="1" node_id="1000" grid_side="bottom"/>
	</CHANX>
	<CHANX side="left" index="5" node_id="1711" segment_id="0" mux_size="3">
		<driver_node type="CHANY" side="bottom" index="2" node_id="2150" segment_id="0"/>
		<driver_node type="CHANY" side="bottom" index="14" node_id="2162" segment_id="0"/>
		<driver_node type="OPIN" side="left" index="2" node_id="677" grid_side="top"/>
	</CHANX>
	<CHANX side="left" index="7" node_id="1721" segment_id="0" mux_size="3">
		<driver_node type="CHANY" side="bottom" index="4" node_id="2152" segment_id="0"/>
		<driver_node type="CHANY" side="bottom" index="22" node_id="2170" segment_id="0"/>
		<driver_node type="OPIN" side="left" index="3" node_id="678" grid_side="top"/>
	</CHANX>
	<CHANX side="left" index="9" node_id="1675" segment_id="0" mux_size="3">
		<driver_node type="CHANY" side="bottom" index="8" node_id="2192" segment_id="0"/>
		<driver_node type="CHANY" side="bottom" index="30" node_id="2178" segment_id="0"/>
		<driver_node type="OPIN" side="left" index="4" node_id="679" grid_side="top"/>
	</CHANX>
	<CHANX side="left" index="11" node_id="1703" segment_id="0" mux_size="2">
		<driver_node type="CHANY" side="bottom" index="10" node_id="2158" segment_id="0"/>
		<driver_node type="CHANY" side="bottom" index="38" node_id="2186" segment_id="0"/>
	</CHANX>
	<CHANX side="left" index="13" node_id="1713" segment_id="0" mux_size="2">
		<driver_node type="CHANY" side="top" index="37" node_id="2199" segment_id="0"/>
		<driver_node type="CHANY" side="bottom" index="12" node_id="2160" segment_id="0"/>
	</CHANX>
	<CHANX side="left" index="15" node_id="1723" segment_id="0" mux_size="2">
		<driver_node type="CHANY" side="top" index="35" node_id="2189" segment_id="0"/>
		<driver_node type="CHANY" side="bottom" index="16" node_id="2194" segment_id="0"/>
	</CHANX>
	<CHANX side="left" index="17" node_id="1683" segment_id="0" mux_size="2">
		<driver_node type="CHANY" side="top" index="33" node_id="2187" segment_id="0"/>
		<driver_node type="CHANY" side="bottom" index="18" node_id="2166" segment_id="0"/>
	</CHANX>
	<CHANX side="left" index="19" node_id="1705" segment_id="0" mux_size="2">
		<driver_node type="CHANY" side="top" index="29" node_id="2197" segment_id="0"/>
		<driver_node type="CHANY" side="bottom" index="20" node_id="2168" segment_id="0"/>
	</CHANX>
	<CHANX side="left" index="21" node_id="1715" segment_id="0" mux_size="3">
		<driver_node type="CHANY" side="top" index="27" node_id="2181" segment_id="0"/>
		<driver_node type="CHANY" side="bottom" index="24" node_id="2196" segment_id="0"/>
		<driver_node type="OPIN" side="left" index="0" node_id="999" grid_side="bottom"/>
	</CHANX>
	<CHANX side="left" index="23" node_id="1725" segment_id="0" mux_size="3">
		<driver_node type="CHANY" side="top" index="25" node_id="2179" segment_id="0"/>
		<driver_node type="CHANY" side="bottom" index="26" node_id="2174" segment_id="0"/>
		<driver_node type="OPIN" side="left" index="1" node_id="1000" grid_side="bottom"/>
	</CHANX>
	<CHANX side="left" index="25" node_id="1691" segment_id="0" mux_size="3">
		<driver_node type="CHANY" side="top" index="21" node_id="2195" segment_id="0"/>
		<driver_node type="CHANY" side="bottom" index="28" node_id="2176" segment_id="0"/>
		<driver_node type="OPIN" side="left" index="2" node_id="677" grid_side="top"/>
	</CHANX>
	<CHANX side="left" index="27" node_id="1707" segment_id="0" mux_size="3">
		<driver_node type="CHANY" side="top" index="19" node_id="2173" segment_id="0"/>
		<driver_node type="CHANY" side="bottom" index="32" node_id="2198" segment_id="0"/>
		<driver_node type="OPIN" side="left" index="3" node_id="678" grid_side="top"/>
	</CHANX>
	<CHANX side="left" index="29" node_id="1717" segment_id="0" mux_size="3">
		<driver_node type="CHANY" side="top" index="17" node_id="2171" segment_id="0"/>
		<driver_node type="CHANY" side="bottom" index="34" node_id="2182" segment_id="0"/>
		<driver_node type="OPIN" side="left" index="4" node_id="679" grid_side="top"/>
	</CHANX>
	<CHANX side="left" index="31" node_id="1727" segment_id="0" mux_size="2">
		<driver_node type="CHANY" side="top" index="13" node_id="2193" segment_id="0"/>
		<driver_node type="CHANY" side="bottom" index="36" node_id="2184" segment_id="0"/>
	</CHANX>
	<CHANX side="left" index="33" node_id="1699" segment_id="0" mux_size="2">
		<driver_node type="CHANY" side="top" index="11" node_id="2165" segment_id="0"/>
		<driver_node type="CHANY" side="top" index="39" node_id="2209" segment_id="0"/>
	</CHANX>
	<CHANX side="left" index="35" node_id="1709" segment_id="0" mux_size="2">
		<driver_node type="CHANY" side="top" index="9" node_id="2163" segment_id="0"/>
		<driver_node type="CHANY" side="top" index="31" node_id="2207" segment_id="0"/>
	</CHANX>
	<CHANX side="left" index="37" node_id="1719" segment_id="0" mux_size="2">
		<driver_node type="CHANY" side="top" index="5" node_id="2191" segment_id="0"/>
		<driver_node type="CHANY" side="top" index="23" node_id="2205" segment_id="0"/>
	</CHANX>
	<CHANX side="left" index="39" node_id="1729" segment_id="0" mux_size="2">
		<driver_node type="CHANY" side="top" index="3" node_id="2157" segment_id="0"/>
		<driver_node type="CHANY" side="top" index="15" node_id="2203" segment_id="0"/>
	</CHANX>
</rr_gsb>
